{
  "$schema": "https://raw.githubusercontent.com/grafana/grafana/main/docs/sources/developers/plugins/plugin.schema.json",
  "type": "panel",
  "name": "Nightingale Chart",
  "id": "vijayprasadmr1-nightingale-panel",
  "info": {
    "keywords": ["panel"],
    "description": "Custom Grafana panel plugin using ECharts (Nightingale Chart)",
    "author": {
      "name": "Vijayprasad"
    },
    "logos": {
      "small": "img/logo.png",
      "large": "img/logo.png"
    },
    "links": [],
   "screenshots": [
  {
    "path": "img/screenshot1.png",
    "name": "Main Panel View"
  }
],
    "version": "1.0.0",
    "updated": "%TODAY%"
  },
  "dependencies": {
    "grafanaDependency": ">=10.4.0",
    "plugins": []
  }
}